{
  "main": {
    "id": "5324373015726ba8",
    "type": "split",
    "children": [
      {
        "id": "4509724f8bf84da7",
        "type": "tabs",
        "dimension": 58.333333333333336,
        "children": [
          {
            "id": "e7a7b303c61786dc",
            "type": "leaf",
            "state": {
              "type": "markdown",
              "state": {
                "file": "Transformatorji.md",
                "mode": "preview",
                "source": true
              },
              "icon": "lucide-file",
              "title": "Transformatorji"
            },
            "group": "e24e164ba1d6ee31"
          }
        ]
      },
      {
        "id": "4448b49e8ef82c65",
        "type": "tabs",
        "dimension": 41.66666666666667,
        "children": [
          {
            "id": "db2e12220259c172",
            "type": "leaf",
            "state": {
              "type": "markdown",
              "state": {
                "file": "Transformatorji.md",
                "mode": "preview",
                "source": true
              },
              "icon": "lucide-file",
              "title": "Transformatorji"
            },
            "group": "e24e164ba1d6ee31"
          }
        ]
      }
    ],
    "direction": "vertical"
  },
  "left": {
    "id": "eb188d34bb1ce1fe",
    "type": "split",
    "children": [
      {
        "id": "666b566a682f1895",
        "type": "tabs",
        "children": [
          {
            "id": "8b183f72515e4dd7",
            "type": "leaf",
            "state": {
              "type": "file-explorer",
              "state": {
                "sortOrder": "alphabetical",
                "autoReveal": false
              },
              "icon": "lucide-folder-closed",
              "title": "Files"
            }
          },
          {
            "id": "a97b979f377e5f85",
            "type": "leaf",
            "state": {
              "type": "search",
              "state": {
                "query": "tag:#complete",
                "matchingCase": false,
                "explainSearch": false,
                "collapseAll": false,
                "extraContext": false,
                "sortOrder": "alphabetical"
              },
              "icon": "lucide-search",
              "title": "Search"
            }
          }
        ]
      }
    ],
    "direction": "horizontal",
    "width": 300,
    "collapsed": true
  },
  "right": {
    "id": "b34b9fa3ad9474dc",
    "type": "split",
    "children": [
      {
        "id": "831b21e889f807bf",
        "type": "tabs",
        "dimension": 76.74418604651163,
        "children": [
          {
            "id": "bea6759642737494",
            "type": "leaf",
            "state": {
              "type": "backlink",
              "state": {
                "file": "Lenzovo pravilo.md",
                "collapseAll": false,
                "extraContext": false,
                "sortOrder": "alphabetical",
                "showSearch": false,
                "searchQuery": "",
                "backlinkCollapsed": false,
                "unlinkedCollapsed": true
              },
              "icon": "links-coming-in",
              "title": "Backlinks for Lenzovo pravilo"
            }
          },
          {
            "id": "827929e1b22e329b",
            "type": "leaf",
            "state": {
              "type": "outgoing-link",
              "state": {
                "file": "Lenzovo pravilo.md",
                "linksCollapsed": false,
                "unlinkedCollapsed": true
              },
              "icon": "links-going-out",
              "title": "Outgoing links from Lenzovo pravilo"
            }
          },
          {
            "id": "4efc0390a931590a",
            "type": "leaf",
            "state": {
              "type": "tag",
              "state": {
                "sortOrder": "frequency",
                "useHierarchy": true,
                "showSearch": false,
                "searchQuery": ""
              },
              "icon": "lucide-tags",
              "title": "Tags"
            }
          },
          {
            "id": "088be638c26d5945",
            "type": "leaf",
            "state": {
              "type": "outline",
              "state": {
                "file": "Excalidraw/Nadomestno vezje transformatorja 2024-11-16 10.41.58.excalidraw.md"
              },
              "icon": "lucide-list",
              "title": "Outline of Nadomestno vezje transformatorja 2024-11-16 10.41.58.excalidraw"
            }
          },
          {
            "id": "f442f2d055b54a7f",
            "type": "leaf",
            "state": {
              "type": "advanced-tables-toolbar",
              "state": {},
              "icon": "spreadsheet",
              "title": "Advanced Tables"
            }
          },
          {
            "id": "5776b097b34ae5f8",
            "type": "leaf",
            "state": {
              "type": "mathpad-view",
              "state": {},
              "icon": "sigma",
              "title": "Mathpad"
            }
          }
        ],
        "currentTab": 5
      },
      {
        "id": "f04e98315356602d",
        "type": "tabs",
        "dimension": 23.255813953488367,
        "children": [
          {
            "id": "db3faec1ebee487f",
            "type": "leaf",
            "state": {
              "type": "mathpad-view",
              "state": {},
              "icon": "sigma",
              "title": "Mathpad"
            }
          }
        ]
      }
    ],
    "direction": "horizontal",
    "width": 384.5,
    "collapsed": true
  },
  "left-ribbon": {
    "hiddenItems": {
      "switcher:Open quick switcher": false,
      "graph:Open graph view": false,
      "command-palette:Open command palette": false,
      "table-editor-obsidian:Advanced Tables Toolbar": false,
      "mathpad:Open Mathpad": false,
      "obsifetch:obsifetch": false,
      "homepage:Open homepage": false,
      "templater-obsidian:Templater": false,
      "obsidian-excalidraw-plugin:Create new drawing": false
    }
  },
  "active": "db2e12220259c172",
  "lastOpenFiles": [
    "Index.md",
    "Magnetni krog.md",
    "Transformatorji.md",
    "Attachments/1741433627.excalidraw.md",
    "Excalidraw/Transformatorji 2024-11-05 16.40.22.excalidraw.md",
    "Excalidraw/Transformatorji 2024-11-05 16.40.22.excalidraw.svg",
    "Attachments/1741433627.excalidraw.svg",
    "Nadomestno vezje transformatorja.md",
    "Excalidraw/Magnetni krog 2024-11-02 09.34.50.excalidraw.md",
    "Efektivne vrednosti.md",
    "BH krivulja.md",
    "Amperov zakon.md",
    "Lenzovo pravilo.md",
    "faradej zakon.md",
    "Attachments/1740836360.excalidraw.md",
    "Excalidraw/Magnetni krog 2024-11-02 13.47.52.excalidraw.md",
    "Attachments/1740836360.excalidraw.svg",
    "Attachments/Pasted Image 20250301142820_368.png",
    "Attachments/Pasted Image 20250301142232_345.png",
    "Attachments/1740830887.excalidraw.md",
    "Attachments/1740830887.excalidraw.svg",
    "Uvod.md",
    "Excalidraw/Magnetni krog 2024-11-02 13.05.34.excalidraw.md",
    "Attachments/Pasted Image 20250301123232_689.png",
    "Attachments",
    "Pasted Image 20250301110603_708.png",
    "Excalidraw/1734772954.excalidraw.md",
    "Excalidraw/Magnetni krog 2024-11-02 12.30.49.excalidraw.md",
    "Excalidraw/1740825604.excalidraw.md",
    "Excalidraw/1740825696.excalidraw.md",
    "Excalidraw/drawing1740825573.excalidraw.md",
    "Excalidraw/1740825696.excalidraw.svg",
    "Excalidraw/1740825604.excalidraw.svg",
    "Excalidraw/Transformatorji 2024-11-05 18.07.54.excalidraw.md",
    "Excalidraw/BH krivulja 2024-11-02 12.41.23.excalidraw.md",
    "Excalidraw/1740140972.excalidraw.md",
    "Pdfs/Lenzovo pravilo.pdf",
    "Pdfs/Transformatorji.pdf",
    "Templates",
    "Pdfs/Amerov zakon.pdf",
    "Pdfs/Magnetni krog.pdf",
    "Pdfs",
    "Excalidraw"
  ]
}